pyfunclog/__init__.py
pyfunclog/async_support.py
pyfunclog/core.py
pyfunclog/decorators.py
pyfunclog/filters.py
pyfunclog/utils.py
pyfunclog-2.0.1.dist-info/licenses/LICENSE
pyfunclog-2.0.1.dist-info/METADATA
pyfunclog-2.0.1.dist-info/WHEEL
pyfunclog-2.0.1.dist-info/entry_points.txt
pyfunclog-2.0.1.dist-info/top_level.txt
pyfunclog-2.0.1.dist-info/RECORD
