Metadata-Version: 2.4
Name: pyfunclog
Version: 2.0.1
Summary: Comprehensive function logging with async support and sensitive data protection
Author-email: sobhan zadehali <sobhan.za47@gmail.com>
License: MIT
Project-URL: Homepage, https://github.com/sobhanzadehali/pyfunclog
Project-URL: Documentation, https://github.com/sobhanzadehali/pyfunclog#readme
Project-URL: Repository, https://github.com/sobhanzadehali/pyfunclog
Project-URL: Issues, https://github.com/sobhanzadehali/pyfunclog/issues
Keywords: logging,debugging,security,async,fastapi,sensitive-data
Classifier: Development Status :: 4 - Beta
Classifier: Intended Audience :: Developers
Classifier: License :: OSI Approved :: MIT License
Classifier: Operating System :: OS Independent
Classifier: Programming Language :: Python :: 3
Classifier: Programming Language :: Python :: 3.7
Classifier: Programming Language :: Python :: 3.8
Classifier: Programming Language :: Python :: 3.9
Classifier: Programming Language :: Python :: 3.10
Classifier: Programming Language :: Python :: 3.11
Classifier: Programming Language :: Python :: 3.12
Classifier: Topic :: Software Development
Classifier: Topic :: Software Development :: Libraries
Classifier: Topic :: Software Development :: Libraries :: Python Modules
Classifier: Topic :: System :: Logging
Classifier: Topic :: Utilities
Requires-Python: >=3.7
License-File: LICENSE
Provides-Extra: fastapi
Requires-Dist: fastapi>=0.68.0; extra == "fastapi"
Requires-Dist: starlette>=0.14.0; extra == "fastapi"
Provides-Extra: dev
Requires-Dist: pytest>=6.0; extra == "dev"
Requires-Dist: pytest-asyncio>=0.21.0; extra == "dev"
Requires-Dist: pytest-cov>=2.0; extra == "dev"
Requires-Dist: black>=22.0; extra == "dev"
Requires-Dist: isort>=5.0; extra == "dev"
Requires-Dist: flake8>=4.0; extra == "dev"
Dynamic: license-file
